sopel_deepl/__init__.py
sopel_deepl/plugin.py
sopel_deepl/util.py
sopel_deepl-0.2.0.dist-info/licenses/COPYING
sopel_deepl-0.2.0.dist-info/METADATA
sopel_deepl-0.2.0.dist-info/WHEEL
sopel_deepl-0.2.0.dist-info/entry_points.txt
sopel_deepl-0.2.0.dist-info/top_level.txt
sopel_deepl-0.2.0.dist-info/RECORD
