Metadata-Version: 2.4
Name: sopel-deepl
Version: 0.2.0
Summary: DeepL translation plugin for Sopel IRC bots.
Author-email: dgw <dgw@technobabbl.es>
License-Expression: EFL-2.0
Project-URL: Homepage, https://github.com/dgw/sopel-deepl
Project-URL: Bug Tracker, https://github.com/dgw/sopel-deepl/issues
Keywords: sopel,plugin,bot,irc,translation
Platform: Linux x86, x86-64
Classifier: Intended Audience :: Developers
Classifier: Intended Audience :: System Administrators
Classifier: Programming Language :: Python :: 3.8
Classifier: Programming Language :: Python :: 3.9
Classifier: Programming Language :: Python :: 3.10
Classifier: Programming Language :: Python :: 3.11
Classifier: Programming Language :: Python :: 3.12
Classifier: Programming Language :: Python :: 3.13
Classifier: Programming Language :: Python :: 3 :: Only
Classifier: Topic :: Communications :: Chat :: Internet Relay Chat
Requires-Python: <4,>=3.8
License-File: COPYING
Requires-Dist: sopel>=8.0
Requires-Dist: deepl~=1.22
Dynamic: license-file
